cfihos_handler/__init__.py
cfihos_handler/_processor.py
cfihos_handler/_reader.py
cfihos_handler/plugin.py
cfihos_handler/framework/__init__.py
cfihos_handler/framework/common/__init__.py
cfihos_handler/framework/common/constants.py
cfihos_handler/framework/common/generic_classes.py
cfihos_handler/framework/common/log.py
cfihos_handler/framework/common/reader.py
cfihos_handler/framework/common/utils.py
cfihos_handler/framework/importer/__init__.py
cfihos_handler/framework/importer/_cfihos2data_model.py
cfihos_handler/framework/importer/base_model_interpreter.py
cfihos_handler/framework/importer/cfihos_loader.py
cfihos_handler/framework/importer/data_sheets_column_mappings.py
cfihos_handler/framework/neat_data_model/__init__.py
cfihos_handler/framework/neat_data_model/model_creater.py
cfihos_handler/framework/processing/__init__.py
cfihos_handler/framework/processing/model_managers/__init__.py
cfihos_handler/framework/processing/model_managers/base_cfihos_manager.py
cfihos_handler/framework/processing/model_managers/model_manager_provider.py
cfihos_handler/framework/processing/model_managers/sparse_model_manager.py
cfihos_handler/framework/processing/processors/__init__.py
cfihos_handler/framework/processing/processors/base_processor.py
cfihos_handler/framework/processing/processors/sparse_properties.py
neat_cfihos_handler-0.1.3.dist-info/licenses/LICENSE
neat_cfihos_handler-0.1.3.dist-info/METADATA
neat_cfihos_handler-0.1.3.dist-info/WHEEL
neat_cfihos_handler-0.1.3.dist-info/entry_points.txt
neat_cfihos_handler-0.1.3.dist-info/top_level.txt
neat_cfihos_handler-0.1.3.dist-info/RECORD
